{"github_data":{"https://github.com/drizzle-team/drizzle-orm":{"contributors":{"count":126,"url":"https://github.com/drizzle-team/drizzle-orm/graphs/contributors"},"description":"Headless TypeScript ORM with a head. Runs on Node, Bun and Deno. Lives on the Edge and yes, it's a JavaScript ORM too 😅","generated_at":"2025-07-19T05:59:00.916457146Z","latest_commit":{"ts":"2025-07-14T16:50:21Z","url":"https://github.com/drizzle-team/drizzle-orm/commit/027921fda2ba61fd6271e49a576e1abd76613fc1"},"participation_stats":[33,35,76,12,12,37,45,31,11,20,23,33,31,9,25,47,53,25,23,25,44,25,20,7,12,23,32,25,3,2,0,4,0,5,18,2,0,0,2,2,0,2,2,5,3,1,0,0,3,0,0,2],"stars":29285,"topics":["bunjs","d1","libsql","litefs","mysql","mysql2","neon","nodejs","orm","postgres","postgresjs","postgresql","sql","sqlite","sqlite3","sqljs","turso","typescript","vercel-postgres"],"url":"https://github.com/drizzle-team/drizzle-orm","first_commit":{"ts":"2022-07-11T00:11:31Z","url":"https://github.com/drizzle-team/drizzle-orm/commit/2fd57381829af3e78ce1ff24fb7cc07e944a3379"},"languages":{"JavaScript":137621,"TypeScript":10190041},"latest_release":{"ts":"2025-07-14T17:08:39Z","url":"https://github.com/drizzle-team/drizzle-orm/releases/tag/0.44.3"},"license":"Apache License 2.0"},"https://github.com/prisma/prisma":{"contributors":{"count":305,"url":"https://github.com/prisma/prisma/graphs/contributors"},"description":"Next-generation ORM for Node.js & TypeScript | PostgreSQL, MySQL, MariaDB, SQL Server, SQLite, MongoDB and CockroachDB","generated_at":"2025-07-19T05:59:59.771862926Z","latest_commit":{"ts":"2025-07-18T15:27:28Z","url":"https://github.com/prisma/prisma/commit/ae2f2e4617405e217c219af6b52176c1d6c811f5"},"participation_stats":[8,1,7,7,6,4,9,4,0,7,2,6,4,3,4,13,8,6,17,13,2,25,3,1,8,10,17,17,13,25,27,30,38,29,40,37,13,28,16,23,18,18,27,21,18,17,14,22,26,26,11,21],"stars":42894,"topics":["cockroachdb","database","javascript","mariadb","mongo","mongodb","mongodb-orm","mssql","mysql","nodejs","orm","postgres","postgresql","prisma","prisma-client","query-builder","sql-server","sqlite","sqlserver","typescript"],"url":"https://github.com/prisma/prisma","first_commit":{"ts":"2019-04-29T18:35:36Z","url":"https://github.com/prisma/prisma/commit/9c076bbfddb709811423d74be933b86ff1e696eb"},"languages":{"Batchfile":270,"Dockerfile":1783,"JavaScript":70632,"PLpgSQL":567,"Shell":5958,"TSQL":258,"TypeScript":6050473},"latest_release":{"ts":"2025-07-15T15:58:08Z","url":"https://github.com/prisma/prisma/releases/tag/6.12.0"},"license":"Apache License 2.0"},"https://github.com/sequelize/sequelize":{"contributors":{"count":1242,"url":"https://github.com/sequelize/sequelize/graphs/contributors"},"description":"Feature-rich ORM for modern Node.js and TypeScript, it supports PostgreSQL (with JSON and JSONB support), MySQL, MariaDB, SQLite, MS SQL Server, Snowflake, Oracle DB (v6), DB2 and DB2 for IBM i.","generated_at":"2025-07-19T06:00:07.729841380Z","latest_commit":{"ts":"2025-07-14T20:28:18Z","url":"https://github.com/sequelize/sequelize/commit/002f6046921b077eb102fcc52a8aed173efd36ce"},"participation_stats":[0,0,0,0,0,0,14,38,9,0,28,15,11,15,18,9,8,10,0,18,13,10,10,3,6,17,11,16,12,14,9,8,17,34,18,13,5,12,14,10,8,6,8,8,16,6,6,10,6,9,7,4],"stars":30086,"topics":["db2-ibm-i","feature-rich","javascript","mariadb","microsoft-sql-server","mssql","mssql-server","mysql","nodejs","oracle-db","orm","postgresql","sequelize","snowflakedb","sql","sqlite","transactions","typescript"],"url":"https://github.com/sequelize/sequelize","first_commit":{"ts":"2010-07-22T19:25:24Z","url":"https://github.com/sequelize/sequelize/commit/fee92083a75c15f5b6cd2d0c2f3bb043ae155e68"},"languages":{"Batchfile":117,"JavaScript":2562195,"Shell":12926,"TypeScript":2644210},"latest_release":{"ts":"2025-03-28T11:35:01Z","url":"https://github.com/sequelize/sequelize/releases/tag/v6.37.7"},"license":"MIT License"},"https://github.com/typeorm/typeorm":{"contributors":{"count":1177,"url":"https://github.com/typeorm/typeorm/graphs/contributors"},"description":"ORM for TypeScript and JavaScript. Supports MySQL, PostgreSQL, MariaDB, SQLite, MS SQL Server, Oracle, SAP Hana, WebSQL databases. Works in NodeJS, Browser, Ionic, Cordova and Electron platforms.","generated_at":"2025-07-19T06:00:17.739637117Z","latest_commit":{"ts":"2025-07-09T06:23:47Z","url":"https://github.com/typeorm/typeorm/commit/f351757a15b9d2bd9d4222c69dcfd2316f46b5d1"},"participation_stats":[0,0,0,0,0,0,0,0,0,0,0,0,0,0,0,1,0,0,3,0,6,6,0,5,20,0,9,4,2,6,2,2,6,7,5,3,19,1,8,2,5,5,13,1,0,10,3,9,5,3,4,0],"stars":35564,"topics":["active-record","cockroachdb","data-mapper","database","electron","hacktoberfest","javascript","mariadb","mysql","oracle","orm","postgresql","react-native","sap","sap-hana","sqlite","sqlserver","typeorm","typescript","websql"],"url":"https://github.com/typeorm/typeorm","first_commit":{"ts":"2016-02-21T06:38:43Z","url":"https://github.com/typeorm/typeorm/commit/4309b8d81040d27c5a4b285376de44c342afa78a"},"languages":{"JavaScript":19158,"TypeScript":9426114},"latest_release":{"ts":"2025-06-19T16:09:18Z","url":"https://github.com/typeorm/typeorm/releases/tag/0.3.25"},"license":"MIT License"}},"items":[{"category":"ORM","homepage_url":"https://orm.drizzle.team/","id":"orm--orm--drizzle","logo":"logos/810555aacc2a8bd920920ef688035bae5d1899d988a3fa114c8713d2074c8fa2.svg","name":"Drizzle","subcategory":"ORM","website":"https://orm.drizzle.team/","description":"A TypeScript-first ORM designed for writing database queries in a SQL-like syntax.","oss":true,"repositories":[{"url":"https://github.com/drizzle-team/drizzle-orm","primary":true}],"twitter_url":"https://x.com/DrizzleOrm"},{"category":"ORM","homepage_url":"https://www.prisma.io/","id":"orm--orm--prisma","logo":"logos/d1e24e513a3b53b047b20eb268235de5def32dc71d9c840b8dc552cab7eee88f.svg","name":"Prisma","subcategory":"ORM","website":"https://www.prisma.io/","description":"A modern ORM for Node.js and TypeScript that simplifies database access and management.","oss":true,"repositories":[{"url":"https://github.com/prisma/prisma","primary":true}],"twitter_url":"https://twitter.com/prisma"},{"category":"ORM","homepage_url":"https://typeorm.io/","id":"orm--orm--typeorm","logo":"logos/cfd7d8c3b265f98e321c7b355acc35306572fccc55e73ee2a5833f59df8936a6.svg","name":"TypeORM","subcategory":"ORM","website":"https://typeorm.io/","description":"TypeORM is an ORM that can run in NodeJS, Browser, Cordova, PhoneGap, Ionic, React Native, NativeScript, Expo, and Electron platforms and can be used with TypeScript and JavaScript (ES2021).","oss":true,"repositories":[{"url":"https://github.com/typeorm/typeorm","primary":true}]},{"category":"ORM","homepage_url":"https://sequelize.org/","id":"orm--orm--sequelize","logo":"logos/fca9b648a3e5c2afd1af823877fcc61d306b9791823481a2839f877085259b5c.svg","name":"Sequelize","subcategory":"ORM","website":"https://sequelize.org/","description":"Sequelize is a modern TypeScript and Node.js ORM for Oracle, Postgres, MySQL, MariaDB, SQLite and SQL Server, and more. Featuring solid transaction support, relations, eager and lazy loading, read replication and more.","oss":true,"repositories":[{"url":"https://github.com/sequelize/sequelize","primary":true}],"twitter_url":"https://twitter.com/SequelizeJS"}]}