{"github_data":{"https://github.com/Leaflet/Leaflet":{"contributors":{"count":1003,"url":"https://github.com/Leaflet/Leaflet/graphs/contributors"},"description":"🍃 JavaScript library for mobile-friendly interactive maps 🇺🇦","generated_at":"2025-07-19T05:58:38.451747750Z","latest_commit":{"ts":"2025-07-18T14:36:02Z","url":"https://github.com/Leaflet/Leaflet/commit/4b40a2a219037af70c77b8ecf6cd2b84514cd890"},"participation_stats":[3,6,0,2,0,0,0,1,0,0,0,1,0,0,0,0,0,0,0,0,0,0,0,0,1,0,0,0,0,0,10,6,12,1,3,2,0,1,3,17,1,8,8,10,2,2,2,0,0,1,7,6],"stars":43184,"topics":["javascript","leaflet","maps"],"url":"https://github.com/Leaflet/Leaflet","first_commit":{"ts":"2010-09-01T14:55:30Z","url":"https://github.com/Leaflet/Leaflet/commit/eb5b7d706b9f439863172c522add77a0193dbda8"},"languages":{"CSS":12414,"HTML":130006,"Handlebars":8765,"JavaScript":990287},"latest_release":{"ts":"2023-05-18T11:12:03Z","url":"https://github.com/Leaflet/Leaflet/releases/tag/v1.9.4"},"license":"BSD 2-Clause \"Simplified\" License"},"https://github.com/openlayers/openlayers":{"contributors":{"count":507,"url":"https://github.com/openlayers/openlayers/graphs/contributors"},"description":"OpenLayers","generated_at":"2025-07-19T05:59:52.665518528Z","latest_commit":{"ts":"2025-07-15T09:09:28Z","url":"https://github.com/openlayers/openlayers/commit/37580bc0cbc311f6371a158c4f51587efb655dea"},"participation_stats":[26,35,36,28,32,22,15,29,21,26,47,19,31,18,19,28,18,23,36,33,29,53,18,22,19,24,17,49,50,51,20,20,28,24,24,24,20,19,21,10,4,26,18,11,18,11,13,35,14,19,17,17],"stars":11981,"topics":["javascript","maps","openlayers"],"url":"https://github.com/openlayers/openlayers","first_commit":{"ts":"2006-05-12T19:35:22Z","url":"https://github.com/openlayers/openlayers/commit/6810d70bddeccb486bbe88b92ee634eb16240e98"},"languages":{"CSS":30401,"HTML":3218,"Handlebars":16554,"JavaScript":6480361,"Shell":5827,"TypeScript":5520},"latest_release":{"ts":"2025-06-16T19:39:34Z","url":"https://github.com/openlayers/openlayers/releases/tag/v10.6.0"},"license":"BSD 2-Clause \"Simplified\" License"}},"items":[{"category":"Libraries","homepage_url":"https://leafletjs.com/","id":"libraries--mapping--leaflet","logo":"logos/7f46c053c84c498798d2142de2044001e59f2261fe936876f9ca5ba16f9e4106.svg","name":"Leaflet","subcategory":"Mapping","website":"https://leafletjs.com/","description":"A lightweight library for creating interactive maps with markers, popups, and tile layers.","oss":true,"repositories":[{"url":"https://github.com/Leaflet/Leaflet","primary":true}],"twitter_url":"https://x.com/LeafletJS"},{"category":"Libraries","homepage_url":"https://openlayers.org/","id":"libraries--mapping--openlayers","logo":"logos/58a1b9d141eac4090aa489b68cc076fc661e78b8263a59a09dd84a8378b9a31a.svg","name":"OpenLayers","subcategory":"Mapping","website":"https://openlayers.org/","description":"A high-performance library for rendering vector and raster maps with advanced features.","oss":true,"repositories":[{"url":"https://github.com/openlayers/openlayers","primary":true}]}]}