{"classification":{"category":{"name":"Backend Frameworks","normalized_name":"backend-frameworks","subcategories":[{"name":"Frameworks","normalized_name":"frameworks"}]}},"foundation":"JavaScript","items":[{"category":"Backend Frameworks","id":"backend-frameworks--frameworks--express-js","name":"Express.js","logo":"logos/acff8a3b73946ada217b5a627dac7b669217ff790529e4df95a5d4c703aaa2df.svg","subcategory":"Frameworks","website":"https://expressjs.com/","description":"A minimal and flexible Node.js framework for building web and API applications.","primary_repository_url":"https://github.com/expressjs/express"},{"category":"Backend Frameworks","id":"backend-frameworks--frameworks--hono","name":"Hono","logo":"logos/23fe0a237ab1ae8b2af3b31df9b5634f597ceb79e8994042bd05ac6629d51e01.svg","subcategory":"Frameworks","website":"https://hono.dev/","description":"A lightweight framework optimized for edge runtime environments and serverless functions.","primary_repository_url":"https://github.com/honojs/hono"},{"category":"Backend Frameworks","id":"backend-frameworks--frameworks--koa","name":"Koa","logo":"logos/0d5772af499f0350d0ad33d7d8ebf89c6fee0af080669c157fc5fa3977cb8ad3.svg","subcategory":"Frameworks","website":"https://koajs.com/","description":"A next-generation web framework for Node.js","primary_repository_url":"https://github.com/koajs/koa"},{"category":"Backend Frameworks","id":"backend-frameworks--frameworks--nestjs","name":"NestJS","logo":"logos/45206120d4c26481870a208faa2d196faec12318bada3df6b062d0c14c2494cf.svg","subcategory":"Frameworks","website":"https://nestjs.com/","description":"A progressive Node.js framework for building efficient, reliable and scalable server-side applications.","primary_repository_url":"https://github.com/nestjs/nest"},{"category":"Backend Frameworks","id":"backend-frameworks--frameworks--fastify","name":"Fastify","logo":"logos/eaeeac7c2817fc75ade4a124cb976c0dde964b2af5a105d17ff69948897a59eb.svg","subcategory":"Frameworks","website":"https://www.fastify.dev/","description":"Fast and low overhead web framework, for Node.js","primary_repository_url":"https://github.com/fastify/fastify"},{"category":"Backend Frameworks","id":"backend-frameworks--frameworks--adonis","name":"Adonis","logo":"logos/f8b7c3dd29257199351182dff8fc667d52881b5193cc0c536c0f23e8db85f9f4.svg","subcategory":"Frameworks","website":"https://adonisjs.com/","description":"AdonisJS is a TypeScript-first web framework for building web apps and API servers. It comes with support for testing, modern tooling, an ecosystem of official packages, and more.","primary_repository_url":"https://github.com/adonisjs/core"},{"category":"Backend Frameworks","id":"backend-frameworks--frameworks--hapi","name":"Hapi","logo":"logos/5d4b02c647e55dafef8912317c5fe4eaed1a9e83fae7a2f63db1a13c5389bb92.svg","subcategory":"Frameworks","website":"https://hapi.dev/","description":"Build powerful, scalable applications, with minimal overhead and full out-of-the-box functionality - your code, your way","primary_repository_url":"https://github.com/hapijs/hapi"}]}